pyfld/Exceptions.py
pyfld/FastLineDetector.py
pyfld/__init__.py
pyfld-0.6.1.dist-info/LICENSE
pyfld-0.6.1.dist-info/METADATA
pyfld-0.6.1.dist-info/WHEEL
pyfld-0.6.1.dist-info/entry_points.txt
pyfld-0.6.1.dist-info/top_level.txt
pyfld-0.6.1.dist-info/RECORD
