Metadata-Version: 2.1
Name: pyfld
Version: 0.6.1
Summary: pyfld
Home-page: https://github.com/tsukada-cs/pyfld
Author: Taiga Tsukada
Author-email: tsukada.cs@gmail.com
Maintainer: Taiga Tsukada
Maintainer-email: tsukada.cs@gmail.com
License: GPLv3+
Platform: UNKNOWN
Classifier: Development Status :: 5 - Production/Stable
Classifier: Programming Language :: Python
Classifier: Programming Language :: Python :: 3.6
Classifier: Programming Language :: Python :: 3.7
Classifier: Programming Language :: Python :: 3.8
Classifier: Programming Language :: Python :: 3.9
Classifier: Operating System :: MacOS :: MacOS X
Classifier: Operating System :: Microsoft :: Windows
Classifier: Operating System :: POSIX :: Linux
Classifier: License :: OSI Approved :: GNU General Public License v3 or later (GPLv3+)
Classifier: Topic :: Scientific/Engineering
Requires-Python: >=3.6
